Microsoft.DTfW.DHL.manifest
TrioMotion_UnifiedAPI.cpython-310-x86_64-linux-gnu.so
dbghelp.dll
libTrioMotion_UnifiedApi-TCP-x64.so
vld_x64.dll
vld_x64.pdb
triomotion_unifiedapi-0.0.0.dist-info/METADATA
triomotion_unifiedapi-0.0.0.dist-info/WHEEL
triomotion_unifiedapi-0.0.0.dist-info/entry_points.txt
triomotion_unifiedapi-0.0.0.dist-info/licenses/LICENSE
triomotion_unifiedapi-0.0.0.dist-info/RECORD
