Metadata-Version: 2.1
Name: TrioMotion_UnifiedAPI
Version: 0.0.0
Summary: Python binding of Trio Unified API
Author-Email: Boris Dachev <bdachev@triomotion.com>
Classifier: Development Status :: 1 - Planning
Classifier: Programming Language :: Python :: 3
Classifier: Programming Language :: C++
Classifier: License :: Other/Proprietary License
Classifier: Operating System :: OS Independent
Project-URL: Homepage, https://github.com/Trio-Motion-Technology/UnifiedAPI
Requires-Python: >=3.8
License-File: LICENSE
